cartes_dictee/__init__.py
cartes_dictee/main.py
cartes_dictee-0.2.0.dist-info/METADATA
cartes_dictee-0.2.0.dist-info/WHEEL
cartes_dictee-0.2.0.dist-info/entry_points.txt
cartes_dictee-0.2.0.dist-info/licenses/LICENSE
cartes_dictee-0.2.0.dist-info/RECORD
