Metadata-Version: 2.4
Name: cartes-dictee
Version: 0.2.0
Summary: Génère des cartes de dictée imprimables à partir de fichiers CSV
Project-URL: Homepage, https://gitlab.com/boileaum/cartes_dictee
Project-URL: Repository, https://gitlab.com/boileaum/cartes_dictee
Author-email: Matthieu Boileau <matthieu.boileau@gmail.com>
License: MIT
License-File: LICENSE
Keywords: A4,cartes,dictée,education,impression
Classifier: Development Status :: 4 - Beta
Classifier: Intended Audience :: Education
Classifier: License :: OSI Approved :: MIT License
Classifier: Operating System :: OS Independent
Classifier: Programming Language :: Python :: 3
Classifier: Topic :: Education
Classifier: Topic :: Printing
Classifier: Topic :: Text Processing :: Markup :: HTML
Requires-Python: >=3.8
